blurpool/__init__.py
blurpool/blurpool.py
blurpool-0.0.1.dist-info/METADATA
blurpool-0.0.1.dist-info/WHEEL
blurpool-0.0.1.dist-info/top_level.txt
blurpool-0.0.1.dist-info/RECORD
