Metadata-Version: 2.1
Name: blurpool
Version: 0.0.1
Requires-Dist: numpy
Requires-Dist: tensorflow
